simple_file_backup/__init__.py
simple_file_backup/__main__.py
simple_file_backup-1.1.1.dist-info/METADATA
simple_file_backup-1.1.1.dist-info/WHEEL
simple_file_backup-1.1.1.dist-info/entry_points.txt
simple_file_backup-1.1.1.dist-info/top_level.txt
simple_file_backup-1.1.1.dist-info/RECORD
