Metadata-Version: 2.1
Name: simple-file-backup
Version: 1.1.1
Summary: Console application for periodically backing up a single file.
Home-page: UNKNOWN
Author: Zsolt Nagy
Author-email: nazsolti@outlook.com
License: GPLv3
Platform: UNKNOWN
Classifier: Programming Language :: Python :: 3
Classifier: License :: OSI Approved :: GNU General Public License v3 (GPLv3)
Classifier: Operating System :: OS Independent
Requires-Python: >=3.8
